pymaker/__init__.py
pymaker-1.0b1.dist-info/LICENSE
pymaker-1.0b1.dist-info/METADATA
pymaker-1.0b1.dist-info/WHEEL
pymaker-1.0b1.dist-info/top_level.txt
pymaker-1.0b1.dist-info/RECORD
